mitene_download.py
mitene_download-0.6.0.dist-info/entry_points.txt
mitene_download-0.6.0.dist-info/licenses/LICENCE
mitene_download-0.6.0.dist-info/WHEEL
mitene_download-0.6.0.dist-info/METADATA
mitene_download-0.6.0.dist-info/RECORD
