Metadata-Version: 2.4
Name: mitene_download
Version: 0.6.0
Summary: Download medias from https://mitene.us/ or https://family-album.com/
Author: Jérome Perrin
Requires-Python: >=3.9
Classifier: License :: OSI Approved :: MIT License
License-File: LICENCE
Requires-Dist: aiohttp[speedups]
Project-URL: Source, https://github.com/perrinjerome/mitene_download
